cantinaUtils/Database.py
cantinaUtils/email_utils.py
cantinaUtils/verify_login.py
cantinaUtils-0.0.6.dist-info/LICENSE
cantinaUtils-0.0.6.dist-info/METADATA
cantinaUtils-0.0.6.dist-info/WHEEL
cantinaUtils-0.0.6.dist-info/top_level.txt
cantinaUtils-0.0.6.dist-info/RECORD
