Metadata-Version: 2.1
Name: cantinaUtils
Version: 0.0.6
Summary: The Utils package for Cantina
Author-email: Matyu9 <mathieu.degueurce@icloud.com>
Project-URL: Homepage, https://github.com/Cantina-Org/CantinaUtils
Project-URL: Issues, https://github.com/Cantina-Org/CantinaUtils/issues
Classifier: Programming Language :: Python :: 3
Classifier: License :: OSI Approved :: MIT License
Classifier: Operating System :: OS Independent
Requires-Python: >=3.8
License-File: LICENSE
